caniuse/__init__.py
caniuse/__main__.py
caniuse/_version.py
caniuse/caniuse.py
caniuse/cli.py
caniuse/constants.py
caniuse/exceptions.py
caniuse/utils.py
pycaniuse-0.0.2.dist-info/METADATA
pycaniuse-0.0.2.dist-info/WHEEL
pycaniuse-0.0.2.dist-info/entry_points.txt
pycaniuse-0.0.2.dist-info/licenses/LICENSE
pycaniuse-0.0.2.dist-info/RECORD
