Metadata-Version: 2.4
Name: pycaniuse
Version: 0.0.2
Summary: Query caniuse.com from the terminal
Project-URL: Homepage, https://github.com/viseshrp/pycaniuse
Project-URL: Repository, https://github.com/viseshrp/pycaniuse
Project-URL: Documentation, https://github.com/viseshrp/pycaniuse/blob/main/README.md
Author-email: Visesh Prasad <viseshrprasad@gmail.com>
License: MIT
License-File: LICENSE
Keywords: python
Classifier: Intended Audience :: Developers
Classifier: Programming Language :: Python
Classifier: Programming Language :: Python :: 3
Classifier: Programming Language :: Python :: 3.9
Classifier: Programming Language :: Python :: 3.10
Classifier: Programming Language :: Python :: 3.11
Classifier: Programming Language :: Python :: 3.12
Classifier: Programming Language :: Python :: 3.13
Classifier: Topic :: Software Development :: Libraries :: Python Modules
Requires-Python: <4.0,>=3.9
Requires-Dist: click>=8.1.1
